watchmen_storage_mssql/__init__.py
watchmen_storage_mssql/data_source_mssql.py
watchmen_storage_mssql/script_builder_mssql.py
watchmen_storage_mssql/storage_mssql.py
watchmen_storage_mssql/storage_mssql_configuration.py
watchmen_storage_mssql/table_creator.py
watchmen_storage_mssql/where_build.py
watchmen_storage_mssql-18.0.1.dist-info/METADATA
watchmen_storage_mssql-18.0.1.dist-info/WHEEL
watchmen_storage_mssql-18.0.1.dist-info/licenses/LICENSE
watchmen_storage_mssql-18.0.1.dist-info/RECORD
